ultimate_hosts_blacklist/input_repo_updater/__init__.py
ultimate_hosts_blacklist/input_repo_updater/administration.py
ultimate_hosts_blacklist/input_repo_updater/authorization.py
ultimate_hosts_blacklist/input_repo_updater/exceptions.py
ultimate_hosts_blacklist/input_repo_updater/pre_loader.py
ultimate_hosts_blacklist/input_repo_updater/cleaner/__init__.py
ultimate_hosts_blacklist/input_repo_updater/cleaner/base.py
ultimate_hosts_blacklist/input_repo_updater/cleaner/pyfunceble.py
ultimate_hosts_blacklist/input_repo_updater/config/__init__.py
ultimate_hosts_blacklist/input_repo_updater/config/infrastructure.py
ultimate_hosts_blacklist/input_repo_updater/config/outputs.py
ultimate_hosts_blacklist/input_repo_updater/config/pyfunceble.py
ultimate_hosts_blacklist/input_repo_updater/installer/__init__.py
ultimate_hosts_blacklist/input_repo_updater/installer/base.py
ultimate_hosts_blacklist/input_repo_updater/installer/domains_list.py
ultimate_hosts_blacklist/input_repo_updater/installer/exceptions.py
ultimate_hosts_blacklist/input_repo_updater/installer/infrastructure.py
ultimate_hosts_blacklist/input_repo_updater/installer/pyfunceble.py
ultimate_hosts_blacklist/input_repo_updater/tester/__init__.py
ultimate_hosts_blacklist/input_repo_updater/tester/base.py
ultimate_hosts_blacklist/input_repo_updater/tester/multiprocess.py
ultimate_hosts_blacklist/input_repo_updater/tester/single.py
ultimate_hosts_blacklist/input_repo_updater/updater/__init__.py
ultimate_hosts_blacklist/input_repo_updater/updater/base.py
ultimate_hosts_blacklist/input_repo_updater/updater/exceptions.py
ultimate_hosts_blacklist/input_repo_updater/updater/pyfunceble.py
ultimate_hosts_blacklist/input_repo_updater/updater/travis.py
ultimate_hosts_blacklist_input_repo_updater-2.6.6.dist-info/LICENSE
ultimate_hosts_blacklist_input_repo_updater-2.6.6.dist-info/METADATA
ultimate_hosts_blacklist_input_repo_updater-2.6.6.dist-info/WHEEL
ultimate_hosts_blacklist_input_repo_updater-2.6.6.dist-info/entry_points.txt
ultimate_hosts_blacklist_input_repo_updater-2.6.6.dist-info/top_level.txt
ultimate_hosts_blacklist_input_repo_updater-2.6.6.dist-info/RECORD
