Metadata-Version: 2.1
Name: ultimate-hosts-blacklist-input-repo-updater
Version: 2.6.6
Summary: The tool to update the input source repositories of the Ultimate-Hosts-Blacklist project.
Home-page: https://github.com/Ultimate-Hosts-Blacklist/dev-center/tree/input-repo-updater
Author: UNKNOWN
Author-email: UNKNOWN
License: MIT
Keywords: Python,hosts,hosts file
Platform: any
Classifier: Environment :: Console
Classifier: Topic :: Internet
Classifier: Development Status :: 5 - Production/Stable
Classifier: Intended Audience :: Developers
Classifier: Programming Language :: Python
Classifier: Programming Language :: Python :: 3
Classifier: License :: OSI Approved :: MIT License
Requires-Dist: colorama
Requires-Dist: domain2idna
Requires-Dist: pyyaml
Requires-Dist: ultimate-hosts-blacklist-helpers (>=1.20.1)
Requires-Dist: ultimate-hosts-blacklist-whitelist
